ats/bin/__init__.py
ats/bin/launcher.py
ats/bin/utils.py
ats/core/__init__.py
ats/core/models/base/__init__.py
ats/core/models/base/app.py
ats/web/__init__.py
ats/web/app.py
ats/web/pages/default.py
cr_2024_ats-0.0.1.dist-info/LICENSE
cr_2024_ats-0.0.1.dist-info/METADATA
cr_2024_ats-0.0.1.dist-info/WHEEL
cr_2024_ats-0.0.1.dist-info/entry_points.txt
cr_2024_ats-0.0.1.dist-info/RECORD
