Metadata-Version: 2.1
Name: cr-2024-ats
Version: 0.0.1
Summary: Almost the Same is Still Different
License: GPL-3.0-or-later
Author: Arnoud Stolk
Requires-Python: >=3.11,<4.0
Classifier: License :: OSI Approved :: GNU General Public License v3 or later (GPLv3+)
Classifier: Programming Language :: Python :: 3
Classifier: Programming Language :: Python :: 3.11
Classifier: Programming Language :: Python :: 3.12
Requires-Dist: argparse (>=1.4.0,<2.0.0)
Requires-Dist: flask (>=3.0.3,<4.0.0)
Requires-Dist: gevent (>=24.2.1,<25.0.0)
